{
  "appPageId" : "fe234450-df3c-4482-ad5c-a062665c7782",
  "componentName" : "siteforce:sldsOneColLayout",
  "id" : "534460e9-d7f3-4015-b847-a57291710eb7",
  "label" : "Topic Catalog",
  "regions" : [ {
    "components" : [ {
      "componentAttributes" : {
        "bannerText" : "",
        "bannerTextWithKnowledge" : "Explore other <a href=\"javascript:void(0)\" class=\"headlineArticles\">articles</a> and <a href=\"javascript:void(0)\" class=\"headlineDiscussions\">discussions</a> on this topic.",
        "bannerTextWithoutKnowledge" : "Explore other <a href=\"javascript:void(0)\" class=\"headlineDiscussions\">discussions</a> on this topic.",
        "pageType" : "",
        "showSubTopics" : true,
        "title" : "Topics",
        "uniqueNameOrId" : ""
      },
      "componentName" : "forceCommunity:headline",
      "id" : "d03f410e-60d9-4f93-ae38-5f0da0a38c1c",
      "renderPriority" : "NEUTRAL",
      "renditionMap" : { },
      "type" : "component"
    } ],
    "id" : "d8749ce3-56b4-485c-8485-cd24903fe380",
    "regionName" : "header",
    "type" : "region"
  }, {
    "components" : [ {
      "componentAttributes" : { },
      "componentName" : "forceCommunity:topicCatalog",
      "id" : "c6c50fd7-c614-4d06-8e30-71fcdd934261",
      "renderPriority" : "NEUTRAL",
      "renditionMap" : { },
      "type" : "component"
    } ],
    "id" : "656ffa59-6325-43f4-9af0-e3ba9d21b8c9",
    "regionName" : "content",
    "type" : "region"
  }, {
    "components" : [ {
      "componentAttributes" : {
        "askCommunityLabel" : "Ask a Question",
        "buttonBgColor" : "",
        "buttonBgHoverColor" : "",
        "buttonBorderColor" : "",
        "buttonRadius" : 0,
        "buttonTextColor" : "",
        "buttonTextHoverColor" : "",
        "buttonTwoBgColor" : "",
        "buttonTwoBgHoverColor" : "",
        "buttonTwoBorderColor" : "",
        "buttonTwoRadius" : 0,
        "buttonTwoTextColor" : "",
        "buttonTwoTextHoverColor" : "",
        "confirmationMessage" : "Got it!",
        "contactSupportLabel" : "Contact Support",
        "followUpPromptLabel" : "Can we close your question?",
        "headerLabel" : "Don't see what you're looking for?",
        "isAskFollowPromptEnabled" : true,
        "isIncludeArticlesEnabled" : false,
        "isIncludeDiscussionsEnabled" : true,
        "isInitialSatisfactionPromptEnabled" : true,
        "isPublisherDeflectionEnabled" : true,
        "maxSuggestions" : 5,
        "satisfactionPromptLabel" : "Did we help to answer your question?",
        "showDetails" : false,
        "showTopics" : true
      },
      "componentName" : "siteforce:napiliFooter",
      "id" : "ce796229-c5dd-4dce-b624-8442130844b6",
      "renderPriority" : "NEUTRAL",
      "renditionMap" : { },
      "type" : "component"
    } ],
    "id" : "fa98fdaa-e679-4680-aabd-0661ca736cc8",
    "regionName" : "footer",
    "type" : "region"
  }, {
    "components" : [ {
      "componentAttributes" : {
        "customHeadTags" : "",
        "description" : "",
        "title" : "Topic Catalog"
      },
      "componentName" : "forceCommunity:seoAssistant",
      "id" : "e06d1b5d-aed8-4a09-9d60-4156df51daab",
      "renditionMap" : { },
      "type" : "component"
    } ],
    "id" : "d7637cdd-d23f-42cf-b091-c66ac1502903",
    "regionName" : "sfdcHiddenRegion",
    "type" : "region"
  } ],
  "themeLayoutType" : "Inner",
  "type" : "view",
  "viewType" : "topic-catalog"
}